{
  "city": "Lucknow",
  "disease": "flu",
  "outbreak_location": "jankipuram",
  "initial_cases": 14,
  "peak_zone": "Hazratganj",
  "immediate_actions": [
    "Deploy rapid response teams to Jankipuram for case investigation and contact tracing.",
    "Alert all healthcare facilities in Lucknow to prepare for potential influx of flu cases and activate emergency protocols.",
    "Initiate city-wide public awareness campaign on flu symptoms, prevention (hand hygiene, respiratory etiquette), and reporting procedures.",
    "Establish a central command center for real-time data monitoring, resource coordination, and public communication.",
    "Ensure adequate supply of antiviral medications, PPE, and testing kits in designated health facilities across Lucknow."
  ],
  "containment_zones": [
    {
      "name": "Jankipuram",
      "level": "red",
      "restrictions": [
        "Strict contact tracing and isolation protocols",
        "Temporary closure of non-essential public gatherings",
        "Mandatory thermal screening at key entry points"
      ],
      "testing_centers": 3,
      "reason": "Origin of flu outbreak, 14 confirmed cases, active community transmission detected."
    },
    {
      "name": "Hazratganj",
      "level": "yellow",
      "restrictions": [
        "Enhanced public health advisories on flu symptoms and prevention",
        "Promotion of hand hygiene and respiratory etiquette"
      ],
      "testing_centers": 1,
      "reason": "No projected cases within 72 hours, maintaining high alert and proactive surveillance."
    },
    {
      "name": "Aminabad",
      "level": "yellow",
      "restrictions": [
        "Enhanced public health advisories on flu symptoms and prevention",
        "Promotion of hand hygiene and respiratory etiquette"
      ],
      "testing_centers": 1,
      "reason": "No projected cases within 72 hours, maintaining high alert and proactive surveillance."
    },
    {
      "name": "Gomti Nagar",
      "level": "yellow",
      "restrictions": [
        "Enhanced public health advisories on flu symptoms and prevention",
        "Promotion of hand hygiene and respiratory etiquette"
      ],
      "testing_centers": 1,
      "reason": "No projected cases within 72 hours, maintaining high alert and proactive surveillance."
    },
    {
      "name": "Alambagh",
      "level": "yellow",
      "restrictions": [
        "Enhanced public health advisories on flu symptoms and prevention",
        "Promotion of hand hygiene and respiratory etiquette"
      ],
      "testing_centers": 1,
      "reason": "No projected cases within 72 hours, maintaining high alert and proactive surveillance."
    },
    {
      "name": "Chowk",
      "level": "yellow",
      "restrictions": [
        "Enhanced public health advisories on flu symptoms and prevention",
        "Promotion of hand hygiene and respiratory etiquette"
      ],
      "testing_centers": 1,
      "reason": "No projected cases within 72 hours, maintaining high alert and proactive surveillance."
    },
    {
      "name": "Aliganj",
      "level": "yellow",
      "restrictions": [
        "Enhanced public health advisories on flu symptoms and prevention",
        "Promotion of hand hygiene and respiratory etiquette"
      ],
      "testing_centers": 1,
      "reason": "No projected cases within 72 hours, maintaining high alert and proactive surveillance."
    },
    {
      "name": "Indira Nagar",
      "level": "yellow",
      "restrictions": [
        "Enhanced public health advisories on flu symptoms and prevention",
        "Promotion of hand hygiene and respiratory etiquette"
      ],
      "testing_centers": 1,
      "reason": "No projected cases within 72 hours, maintaining high alert and proactive surveillance."
    },
    {
      "name": "Rajajipuram",
      "level": "yellow",
      "restrictions": [
        "Enhanced public health advisories on flu symptoms and prevention",
        "Promotion of hand hygiene and respiratory etiquette"
      ],
      "testing_centers": 1,
      "reason": "No projected cases within 72 hours, maintaining high alert and proactive surveillance."
    }
  ],
  "resource_plan": {
    "Jankipuram": {
      "doctors": 9,
      "testing_kits": 225,
      "ambulances": 3,
      "beds_available": 0,
      "icu_beds": 0,
      "beds_reserved": 0,
      "hospitals": []
    },
    "Hazratganj": {
      "doctors": 2,
      "testing_kits": 50,
      "ambulances": 1,
      "beds_available": 650,
      "icu_beds": 40,
      "beds_reserved": 32,
      "hospitals": [
        "Ram Manohar Lohia Hospital"
      ]
    },
    "Aminabad": {
      "doctors": 2,
      "testing_kits": 50,
      "ambulances": 1,
      "beds_available": 0,
      "icu_beds": 0,
      "beds_reserved": 0,
      "hospitals": []
    },
    "Gomti Nagar": {
      "doctors": 2,
      "testing_kits": 50,
      "ambulances": 1,
      "beds_available": 800,
      "icu_beds": 105,
      "beds_reserved": 40,
      "hospitals": [
        "Sahara Hospital",
        "Medanta Hospital"
      ]
    },
    "Alambagh": {
      "doctors": 2,
      "testing_kits": 50,
      "ambulances": 1,
      "beds_available": 180,
      "icu_beds": 12,
      "beds_reserved": 9,
      "hospitals": [
        "Vivekananda Hospital"
      ]
    },
    "Chowk": {
      "doctors": 2,
      "testing_kits": 50,
      "ambulances": 1,
      "beds_available": 4200,
      "icu_beds": 155,
      "beds_reserved": 210,
      "hospitals": [
        "King George Medical University",
        "Balrampur Hospital"
      ]
    },
    "Aliganj": {
      "doctors": 2,
      "testing_kits": 50,
      "ambulances": 1,
      "beds_available": 200,
      "icu_beds": 15,
      "beds_reserved": 10,
      "hospitals": [
        "Civil Hospital Aliganj"
      ]
    },
    "Indira Nagar": {
      "doctors": 2,
      "testing_kits": 50,
      "ambulances": 1,
      "beds_available": 80,
      "icu_beds": 10,
      "beds_reserved": 4,
      "hospitals": [
        "Apollo Clinic"
      ]
    },
    "Rajajipuram": {
      "doctors": 2,
      "testing_kits": 50,
      "ambulances": 1,
      "beds_available": 250,
      "icu_beds": 18,
      "beds_reserved": 12,
      "hospitals": [
        "District Hospital Rajajipuram"
      ]
    }
  },
  "alerts": [
    {
      "type": "public_sms",
      "message": "सावधान: Jankipuram में flu के मामले मिले हैं। घर में पानी जमा न होने दें। नजदीकी टेस्टिंग सेंटर जाएं।"
    }
  ]
}